{
  "title": "Beef Jerky",
  "source": "Joe Beef",
  "servings": "",
  "categories": [
    "Snacks"
  ],
  "ingredients": [
    "2.2pounds (1 kg) beef eye round, frozen for 30 minutes before slicing",
    "For the marinade",
    "\u00bdcup (120 ml) Worcestershire Sauce (this page)",
    "\u00bdcup (170 ml) maple syrup",
    "1teaspoon ground white pepper",
    "1teaspoon Frank\u2019s Red Hot sauce",
    "1teaspoon onion powder",
    "1teaspoon sea salt"
  ],
  "directions": [
    "1. Slice the beef against the grain into \u00bc-inch-thick (6-mm-thick) slices. Combine all the marinade ingredients.",
    "2. Marinate the meat in the mixture for 1 or more days (the longer you marinate, the deeper the flavor).",
    "3. Cook in a warm smoker or a 160\u00b0F (70\u00b0C) oven for 5 to 8 hours, or dehydrate in a dehydrator set at 140\u00b0F (60\u00b0C) for 6 to 7\u00bd hours, or until the desired texture is achieved (depends on marbling of the meat and the thickness of the cuts you use)."
  ]
}