{
  "title": "Recipe Remake: Caffe Panna\u2019s Red Flag",
  "source": "Eating.nyc",
  "servings": "",
  "categories": [
    "***NEED TO MAKE",
    "Ice Cream"
  ],
  "ingredients": [
    "Here\u2019s What You\u2019ll Need For 6 Pints:",
    "4cups whole milk",
    "4cups heavy cream",
    "1stick cream cheese",
    "1 \u00becup sugar",
    "1 \u00bccup corn syrup, tapioca syrup, or maple syrup",
    "1tsp salt",
    "Strawberry preserves",
    "For graham crunch:",
    "3packs of graham crackers",
    "3sticks of butter",
    "1 \u00bccup sugar",
    "Salt"
  ],
  "directions": [
    "Directions For the Graham Crunch:",
    "1. Preheat oven to 325 and line a baking sheet with butter.",
    "2.In a heated pot, add your butter and mix until browned.",
    "3. Combine sugar and a pinch of salt and mix until a grainy texture forms. Then, add in your graham crackers!",
    "4.Lay out on baking sheet and place in oven for 7-10 minutes.",
    "Directions For the Ice Cream:",
    "1. Combine one cup of milk with cream cheese into a blender until it\u2019s fully mixed in. Pour into ice cream maker.",
    "2.Combine sugar, heavy cream, salt and remaining whole milk into ice cream machine.",
    "3. Press start and let the magic happen!",
    "4. Once it\u2019s done, transfer to a bowl and allow to freeze for at least 3 hours.",
    "5. Top with preserves and graham crunch and enjoy!"
  ]
}