{
  "title": "Smashed Cucumbers",
  "source": "A Very Chinese Cookbook - Kevin Pang",
  "servings": "Serves: 4",
  "categories": [
    "A Very Chinese Cookbook - Kevin Pang",
    "Chinese"
  ],
  "ingredients": [
    "- 2 (14-ounce) English cucumbers, ends trimmed",
    "- 1 1/2 teaspoons kosher salt",
    "- 4 teaspoons Chinese black vinegar",
    "- 1 teaspoon garlic, minced to paste",
    "- 1 tablespoon soy sauce",
    "- 2 teaspoons toasted sesame oil",
    "- 1 teaspoon sugar",
    "- 1 teaspoon sesame seeds, toasted",
    "- Chili oil (optional)"
  ],
  "directions": [
    "1. Cut cucumbers crosswise into 3- to 4-inch lengths and place in 1-gallon zipper-lock bag. Seal bag. Using small skillet or rolling pin, firmly but gently smash cucumbers until flattened and split lengthwise into 3 to 4 spears each. Tear spears into rough 1-inch pieces and transfer to colander set in large bowl. Toss cucumbers with salt and let sit for at least 15 minutes or up to 30 minutes.",
    "2. Meanwhile, whisk vinegar and garlic together in medium bowl and let sit for at least 5 minutes or up to 15 minutes.",
    "3. Whisk soy sauce, oil, and sugar into vinegar mixture until sugar has dissolved. Add cucumbers, discarding any extracted liquid, and sesame seeds to bowl with dressing and toss to combine. Drizzle with chili oil, if desired, and serve immediately."
  ]
}